pytowhl/__init__.py
pytowhl/pytowhl.py
pytowhl-0.0.4.dist-info/METADATA
pytowhl-0.0.4.dist-info/WHEEL
pytowhl-0.0.4.dist-info/top_level.txt
pytowhl-0.0.4.dist-info/RECORD
