Metadata-Version: 2.1
Name: pytowhl
Version: 0.0.4
Requires-Dist: logclshelper
Requires-Dist: syshelper
Requires-Dist: venvhelper
